mystran_validation/__init__.py
mystran_validation/cli.py
mystran_validation/conftest_ref.py
mystran_validation/utils.py
mystran_validation/xml_junit2html.py
mystran_validation/data/__init__.py
mystran_validation/data/bulk_model.nas
mystran_validation/data/custom.css
mystran_validation/data/html_index.j2
mystran_validation/data/html_template.j2
mystran_validation/data/test_bar.ini
mystran_validation/data/test_case_03.op2
mystran_validation/parsers/__init__.py
mystran_validation/parsers/nastran_op2.py
mystran_validation-0.18.0.data/data/mystran_validation/data/bulk_model.nas
mystran_validation-0.18.0.data/data/mystran_validation/data/custom.css
mystran_validation-0.18.0.data/data/mystran_validation/data/html_index.j2
mystran_validation-0.18.0.data/data/mystran_validation/data/html_template.j2
mystran_validation-0.18.0.data/data/mystran_validation/data/test_bar.ini
mystran_validation-0.18.0.data/data/mystran_validation/data/test_case_03.op2
mystran_validation-0.18.0.dist-info/AUTHORS.rst
mystran_validation-0.18.0.dist-info/LICENSE
mystran_validation-0.18.0.dist-info/METADATA
mystran_validation-0.18.0.dist-info/WHEEL
mystran_validation-0.18.0.dist-info/entry_points.txt
mystran_validation-0.18.0.dist-info/top_level.txt
mystran_validation-0.18.0.dist-info/RECORD
