Metadata-Version: 2.1
Name: mystran-validation
Version: 0.18.0
Summary: Python framework for MYSTRAN validation
Home-page: UNKNOWN
Author: Nicolas Cordier
Author-email: nicolas.cordier@numeric-gmbh.ch
License: MIT license
Keywords: mystran_validation
Platform: UNKNOWN
Classifier: Development Status :: 2 - Pre-Alpha
Classifier: Intended Audience :: Developers
Classifier: License :: OSI Approved :: MIT License
Classifier: Natural Language :: English
Classifier: Programming Language :: Python :: 3.8
Requires-Python: >=3.8
Requires-Dist: pytest
Requires-Dist: pytest-runner
Requires-Dist: pytest-xdist
Requires-Dist: appdirs
Requires-Dist: flake8
Requires-Dist: psutil
Requires-Dist: openpyxl
Requires-Dist: colorama
Requires-Dist: Click
Requires-Dist: pandas
Requires-Dist: pynastran
Requires-Dist: femap-neutral-parser (>=0.11)
Requires-Dist: junit2html
